fkassa/__init__.py
fkassa/api.py
fkassa/enums.py
fkassa/exceptions.py
fkassa/models.py
fkassa-0.0.3.dist-info/licenses/LICENSE
fkassa-0.0.3.dist-info/METADATA
fkassa-0.0.3.dist-info/WHEEL
fkassa-0.0.3.dist-info/top_level.txt
fkassa-0.0.3.dist-info/RECORD
