Metadata-Version: 2.4
Name: fkassa
Version: 0.0.3
Summary: FreeKassa Python SDK
Home-page: https://github.com/makarworld/fkassa.git
Download-URL: https://github.com/makarworld/fkassa/archive/refs/tags/v0.0.3.zip
Author: abuztrade
Author-email: abuztrade.work@gmail.com
License: MIT License
Project-URL: Bug Reports, https://github.com/makarworld/fkassa/issues
Project-URL: Source, https://github.com/makarworld/fkassa
Keywords: freekassa,freekassa api,freekassa ru,freekassa com,freekassa net,freekassa ru
Classifier: Development Status :: 4 - Beta
Classifier: Topic :: Communications :: Email
Classifier: Operating System :: OS Independent
Classifier: License :: OSI Approved :: MIT License
Classifier: Programming Language :: Python :: 3
Classifier: Programming Language :: Python :: 3.6
Classifier: Programming Language :: Python :: 3.7
Classifier: Programming Language :: Python :: 3.8
Classifier: Programming Language :: Python :: 3.9
Classifier: Programming Language :: Python :: 3.10
Classifier: Programming Language :: Python :: 3.11
Classifier: Programming Language :: Python :: 3.12
Classifier: Programming Language :: Python :: 3.13
Classifier: Intended Audience :: Developers
Classifier: Intended Audience :: Customer Service
Classifier: Intended Audience :: Financial and Insurance Industry
Requires-Python: >=3.6.0
License-File: LICENSE
Requires-Dist: requests
Requires-Dist: pydantic
Dynamic: author
Dynamic: author-email
Dynamic: classifier
Dynamic: description
Dynamic: description-content-type
Dynamic: download-url
Dynamic: home-page
Dynamic: keywords
Dynamic: license
Dynamic: license-file
Dynamic: project-url
Dynamic: requires-dist
Dynamic: requires-python
Dynamic: summary
